indicatorcalc/__init__.py
indicatorcalc/indicatorcalc.py
indicatorcalc-0.1a30.dist-info/METADATA
indicatorcalc-0.1a30.dist-info/RECORD
indicatorcalc-0.1a30.dist-info/WHEEL
indicatorcalc-0.1a30.dist-info/top_level.txt
indicatorcalc_redux/__init__.py
indicatorcalc_redux/indicatorcalc_redux.py
